protoc/__init__.py
protoc/__main__.py
protoc/data/readme.txt
protoc/data/bin/protoc
protoc/data/include/google/protobuf/any.proto
protoc/data/include/google/protobuf/api.proto
protoc/data/include/google/protobuf/cpp_features.proto
protoc/data/include/google/protobuf/descriptor.proto
protoc/data/include/google/protobuf/duration.proto
protoc/data/include/google/protobuf/empty.proto
protoc/data/include/google/protobuf/field_mask.proto
protoc/data/include/google/protobuf/go_features.proto
protoc/data/include/google/protobuf/java_features.proto
protoc/data/include/google/protobuf/source_context.proto
protoc/data/include/google/protobuf/struct.proto
protoc/data/include/google/protobuf/timestamp.proto
protoc/data/include/google/protobuf/type.proto
protoc/data/include/google/protobuf/wrappers.proto
protoc/data/include/google/protobuf/compiler/plugin.proto
protoc_wheel_0-30.2.dist-info/LICENSE
protoc_wheel_0-30.2.dist-info/METADATA
protoc_wheel_0-30.2.dist-info/WHEEL
protoc_wheel_0-30.2.dist-info/entry_points.txt
protoc_wheel_0-30.2.dist-info/top_level.txt
protoc_wheel_0-30.2.dist-info/RECORD
